<?xml version="1.0" encoding="utf-8" ?>
<dwsync>
<file name="address-book.svg" server="unoriginal.studio//var/www/html/" local="133233016239496373" remote="133233018930000000" Dst="2" />
<file name="address-card.svg" server="unoriginal.studio//var/www/html/" local="133233016239786250" remote="133233018930000000" Dst="2" />
<file name="bell-slash.svg" server="unoriginal.studio//var/www/html/" local="133233016240065436" remote="133233018930000000" Dst="2" />
<file name="bell.svg" server="unoriginal.studio//var/www/html/" local="133233016240353926" remote="133233018930000000" Dst="2" />
<file name="bookmark.svg" server="unoriginal.studio//var/www/html/" local="133233016240677275" remote="133233018940000000" Dst="2" />
<file name="building.svg" server="unoriginal.studio//var/www/html/" local="133233016241030650" remote="133233018940000000" Dst="2" />
<file name="calendar-check.svg" server="unoriginal.studio//var/www/html/" local="133233016241405927" remote="133233018940000000" Dst="2" />
<file name="calendar-days.svg" server="unoriginal.studio//var/www/html/" local="133233016241942650" remote="133233018940000000" Dst="2" />
<file name="calendar-minus.svg" server="unoriginal.studio//var/www/html/" local="133233016242655542" remote="133233018940000000" Dst="2" />
<file name="calendar-plus.svg" server="unoriginal.studio//var/www/html/" local="133233016243030748" remote="133233018940000000" Dst="2" />
<file name="calendar-xmark.svg" server="unoriginal.studio//var/www/html/" local="133233016243336691" remote="133233018940000000" Dst="2" />
<file name="calendar.svg" server="unoriginal.studio//var/www/html/" local="133233016243621142" remote="133233018950000000" Dst="2" />
<file name="chart-bar.svg" server="unoriginal.studio//var/www/html/" local="133233016243895319" remote="133233018950000000" Dst="2" />
<file name="chess-bishop.svg" server="unoriginal.studio//var/www/html/" local="133233016244130782" remote="133233018950000000" Dst="2" />
<file name="chess-king.svg" server="unoriginal.studio//var/www/html/" local="133233016244385253" remote="133233018950000000" Dst="2" />
<file name="chess-knight.svg" server="unoriginal.studio//var/www/html/" local="133233016244630785" remote="133233018950000000" Dst="2" />
<file name="chess-pawn.svg" server="unoriginal.studio//var/www/html/" local="133233016244915577" remote="133233018950000000" Dst="2" />
<file name="chess-queen.svg" server="unoriginal.studio//var/www/html/" local="133233016245197828" remote="133233018950000000" Dst="2" />
<file name="chess-rook.svg" server="unoriginal.studio//var/www/html/" local="133233016245476002" remote="133233018950000000" Dst="2" />
<file name="circle-check.svg" server="unoriginal.studio//var/www/html/" local="133233016245736184" remote="133233018950000000" Dst="2" />
<file name="circle-dot.svg" server="unoriginal.studio//var/www/html/" local="133233016246016135" remote="133233018960000000" Dst="2" />
<file name="circle-down.svg" server="unoriginal.studio//var/www/html/" local="133233016246255273" remote="133233018960000000" Dst="2" />
<file name="circle-left.svg" server="unoriginal.studio//var/www/html/" local="133233016246480840" remote="133233018960000000" Dst="2" />
<file name="circle-pause.svg" server="unoriginal.studio//var/www/html/" local="133233016246763706" remote="133233018960000000" Dst="2" />
<file name="circle-play.svg" server="unoriginal.studio//var/www/html/" local="133233016247074979" remote="133233018960000000" Dst="2" />
<file name="circle-question.svg" server="unoriginal.studio//var/www/html/" local="133233016247335628" remote="133233018960000000" Dst="2" />
<file name="circle-right.svg" server="unoriginal.studio//var/www/html/" local="133233016247595262" remote="133233018960000000" Dst="2" />
<file name="circle-stop.svg" server="unoriginal.studio//var/www/html/" local="133233016247835818" remote="133233018960000000" Dst="2" />
<file name="circle-up.svg" server="unoriginal.studio//var/www/html/" local="133233016248065865" remote="133233018970000000" Dst="2" />
<file name="circle-user.svg" server="unoriginal.studio//var/www/html/" local="133233016248329591" remote="133233018970000000" Dst="2" />
<file name="circle-xmark.svg" server="unoriginal.studio//var/www/html/" local="133233016248580289" remote="133233018970000000" Dst="2" />
<file name="circle.svg" server="unoriginal.studio//var/www/html/" local="133233016248830978" remote="133233018970000000" Dst="2" />
<file name="clipboard.svg" server="unoriginal.studio//var/www/html/" local="133233016249064729" remote="133233018970000000" Dst="2" />
<file name="clock.svg" server="unoriginal.studio//var/www/html/" local="133233016249315465" remote="133233018970000000" Dst="2" />
<file name="clone.svg" server="unoriginal.studio//var/www/html/" local="133233016249591012" remote="133233018970000000" Dst="2" />
<file name="closed-captioning.svg" server="unoriginal.studio//var/www/html/" local="133233016249814901" remote="133233018970000000" Dst="2" />
<file name="comment-dots.svg" server="unoriginal.studio//var/www/html/" local="133233016250084635" remote="133233018970000000" Dst="2" />
<file name="comment.svg" server="unoriginal.studio//var/www/html/" local="133233016250346204" remote="133233018980000000" Dst="2" />
<file name="comments.svg" server="unoriginal.studio//var/www/html/" local="133233016250607899" remote="133233018980000000" Dst="2" />
<file name="compass.svg" server="unoriginal.studio//var/www/html/" local="133233016250882591" remote="133233018980000000" Dst="2" />
<file name="copy.svg" server="unoriginal.studio//var/www/html/" local="133233016251125059" remote="133233018980000000" Dst="2" />
<file name="copyright.svg" server="unoriginal.studio//var/www/html/" local="133233016251390937" remote="133233018980000000" Dst="2" />
<file name="credit-card.svg" server="unoriginal.studio//var/www/html/" local="133233016251674878" remote="133233018980000000" Dst="2" />
<file name="envelope-open.svg" server="unoriginal.studio//var/www/html/" local="133233016251950753" remote="133233018980000000" Dst="2" />
<file name="envelope.svg" server="unoriginal.studio//var/www/html/" local="133233016252210465" remote="133233018980000000" Dst="2" />
<file name="eye-slash.svg" server="unoriginal.studio//var/www/html/" local="133233016252504810" remote="133233018980000000" Dst="2" />
<file name="eye.svg" server="unoriginal.studio//var/www/html/" local="133233016252745578" remote="133233018990000000" Dst="2" />
<file name="face-angry.svg" server="unoriginal.studio//var/www/html/" local="133233016252996398" remote="133233018990000000" Dst="2" />
<file name="face-dizzy.svg" server="unoriginal.studio//var/www/html/" local="133233016253251486" remote="133233018990000000" Dst="2" />
<file name="face-flushed.svg" server="unoriginal.studio//var/www/html/" local="133233016253469789" remote="133233018990000000" Dst="2" />
<file name="face-frown-open.svg" server="unoriginal.studio//var/www/html/" local="133233016253720266" remote="133233018990000000" Dst="2" />
<file name="face-frown.svg" server="unoriginal.studio//var/www/html/" local="133233016253984418" remote="133233018990000000" Dst="2" />
<file name="face-grimace.svg" server="unoriginal.studio//var/www/html/" local="133233016254250315" remote="133233018990000000" Dst="2" />
<file name="face-grin-beam-sweat.svg" server="unoriginal.studio//var/www/html/" local="133233016254505862" remote="133233018990000000" Dst="2" />
<file name="face-grin-beam.svg" server="unoriginal.studio//var/www/html/" local="133233016254771157" remote="133233018990000000" Dst="2" />
<file name="face-grin-hearts.svg" server="unoriginal.studio//var/www/html/" local="133233016255035085" remote="133233019000000000" Dst="2" />
<file name="face-grin-squint-tears.svg" server="unoriginal.studio//var/www/html/" local="133233016255330104" remote="133233019000000000" Dst="2" />
<file name="face-grin-squint.svg" server="unoriginal.studio//var/www/html/" local="133233016255611890" remote="133233019000000000" Dst="2" />
<file name="face-grin-stars.svg" server="unoriginal.studio//var/www/html/" local="133233016255887116" remote="133233019000000000" Dst="2" />
<file name="face-grin-tears.svg" server="unoriginal.studio//var/www/html/" local="133233016256166190" remote="133233019000000000" Dst="2" />
<file name="face-grin-tongue-squint.svg" server="unoriginal.studio//var/www/html/" local="133233016256404562" remote="133233019000000000" Dst="2" />
<file name="face-grin-tongue-wink.svg" server="unoriginal.studio//var/www/html/" local="133233016256664644" remote="133233019000000000" Dst="2" />
<file name="face-grin-tongue.svg" server="unoriginal.studio//var/www/html/" local="133233016256920015" remote="133233019000000000" Dst="2" />
<file name="face-grin-wide.svg" server="unoriginal.studio//var/www/html/" local="133233016257135578" remote="133233019000000000" Dst="2" />
<file name="face-grin-wink.svg" server="unoriginal.studio//var/www/html/" local="133233016257365039" remote="133233019010000000" Dst="2" />
<file name="face-grin.svg" server="unoriginal.studio//var/www/html/" local="133233016257605775" remote="133233019010000000" Dst="2" />
<file name="face-kiss-beam.svg" server="unoriginal.studio//var/www/html/" local="133233016257846040" remote="133233019010000000" Dst="2" />
<file name="face-kiss-wink-heart.svg" server="unoriginal.studio//var/www/html/" local="133233016258073001" remote="133233019010000000" Dst="2" />
<file name="face-kiss.svg" server="unoriginal.studio//var/www/html/" local="133233016258364559" remote="133233019010000000" Dst="2" />
<file name="face-laugh-beam.svg" server="unoriginal.studio//var/www/html/" local="133233016258655945" remote="133233019010000000" Dst="2" />
<file name="face-laugh-squint.svg" server="unoriginal.studio//var/www/html/" local="133233016258957018" remote="133233019010000000" Dst="2" />
<file name="face-laugh-wink.svg" server="unoriginal.studio//var/www/html/" local="133233016259264997" remote="133233019010000000" Dst="2" />
<file name="face-laugh.svg" server="unoriginal.studio//var/www/html/" local="133233016259530565" remote="133233019010000000" Dst="2" />
<file name="face-meh-blank.svg" server="unoriginal.studio//var/www/html/" local="133233016259786643" remote="133233019020000000" Dst="2" />
<file name="face-meh.svg" server="unoriginal.studio//var/www/html/" local="133233016260290638" remote="133233019020000000" Dst="2" />
<file name="face-rolling-eyes.svg" server="unoriginal.studio//var/www/html/" local="133233016260034829" remote="133233019020000000" Dst="2" />
<file name="face-sad-cry.svg" server="unoriginal.studio//var/www/html/" local="133233016260555082" remote="133233019020000000" Dst="2" />
<file name="face-sad-tear.svg" server="unoriginal.studio//var/www/html/" local="133233016260845977" remote="133233019020000000" Dst="2" />
<file name="face-smile-beam.svg" server="unoriginal.studio//var/www/html/" local="133233016261146875" remote="133233019020000000" Dst="2" />
<file name="face-smile-wink.svg" server="unoriginal.studio//var/www/html/" local="133233016261409630" remote="133233019020000000" Dst="2" />
<file name="face-smile.svg" server="unoriginal.studio//var/www/html/" local="133233016261721764" remote="133233019020000000" Dst="2" />
<file name="face-surprise.svg" server="unoriginal.studio//var/www/html/" local="133233016262020640" remote="133233019020000000" Dst="2" />
<file name="face-tired.svg" server="unoriginal.studio//var/www/html/" local="133233016262371586" remote="133233019030000000" Dst="2" />
<file name="file-audio.svg" server="unoriginal.studio//var/www/html/" local="133233016262732715" remote="133233019030000000" Dst="2" />
<file name="file-code.svg" server="unoriginal.studio//var/www/html/" local="133233016263006942" remote="133233019030000000" Dst="2" />
<file name="file-excel.svg" server="unoriginal.studio//var/www/html/" local="133233016263276150" remote="133233019030000000" Dst="2" />
<file name="file-image.svg" server="unoriginal.studio//var/www/html/" local="133233016263514883" remote="133233019030000000" Dst="2" />
<file name="file-lines.svg" server="unoriginal.studio//var/www/html/" local="133233016263770228" remote="133233019030000000" Dst="2" />
<file name="file-pdf.svg" server="unoriginal.studio//var/www/html/" local="133233016264014933" remote="133233019030000000" Dst="2" />
<file name="file-powerpoint.svg" server="unoriginal.studio//var/www/html/" local="133233016264259978" remote="133233019030000000" Dst="2" />
<file name="file-video.svg" server="unoriginal.studio//var/www/html/" local="133233016264495033" remote="133233019030000000" Dst="2" />
<file name="file-word.svg" server="unoriginal.studio//var/www/html/" local="133233016264745355" remote="133233019040000000" Dst="2" />
<file name="file-zipper.svg" server="unoriginal.studio//var/www/html/" local="133233016264995007" remote="133233019040000000" Dst="2" />
<file name="file.svg" server="unoriginal.studio//var/www/html/" local="133233016265224071" remote="133233019040000000" Dst="2" />
<file name="flag.svg" server="unoriginal.studio//var/www/html/" local="133233016265445241" remote="133233019040000000" Dst="2" />
<file name="floppy-disk.svg" server="unoriginal.studio//var/www/html/" local="133233016265674605" remote="133233019040000000" Dst="2" />
<file name="folder-closed.svg" server="unoriginal.studio//var/www/html/" local="133233016265920133" remote="133233019040000000" Dst="2" />
<file name="folder-open.svg" server="unoriginal.studio//var/www/html/" local="133233016266186107" remote="133233019040000000" Dst="2" />
<file name="folder.svg" server="unoriginal.studio//var/www/html/" local="133233016266455123" remote="133233019050000000" Dst="2" />
<file name="font-awesome.svg" server="unoriginal.studio//var/www/html/" local="133233016266752197" remote="133233019050000000" Dst="2" />
<file name="futbol.svg" server="unoriginal.studio//var/www/html/" local="133233016267061308" remote="133233019050000000" Dst="2" />
<file name="gem.svg" server="unoriginal.studio//var/www/html/" local="133233016267402283" remote="133233019050000000" Dst="2" />
<file name="hand-back-fist.svg" server="unoriginal.studio//var/www/html/" local="133233016267910302" remote="133233019050000000" Dst="2" />
<file name="hand-lizard.svg" server="unoriginal.studio//var/www/html/" local="133233016268352800" remote="133233019050000000" Dst="2" />
<file name="hand-peace.svg" server="unoriginal.studio//var/www/html/" local="133233016268749186" remote="133233019050000000" Dst="2" />
<file name="hand-point-down.svg" server="unoriginal.studio//var/www/html/" local="133233016269161486" remote="133233019050000000" Dst="2" />
<file name="hand-point-left.svg" server="unoriginal.studio//var/www/html/" local="133233016269517351" remote="133233019060000000" Dst="2" />
<file name="hand-point-right.svg" server="unoriginal.studio//var/www/html/" local="133233016269816331" remote="133233019060000000" Dst="2" />
<file name="hand-point-up.svg" server="unoriginal.studio//var/www/html/" local="133233016270100381" remote="133233019060000000" Dst="2" />
<file name="hand-pointer.svg" server="unoriginal.studio//var/www/html/" local="133233016270385512" remote="133233019060000000" Dst="2" />
<file name="hand-scissors.svg" server="unoriginal.studio//var/www/html/" local="133233016270646246" remote="133233019060000000" Dst="2" />
<file name="hand-spock.svg" server="unoriginal.studio//var/www/html/" local="133233016270920429" remote="133233019060000000" Dst="2" />
<file name="hand.svg" server="unoriginal.studio//var/www/html/" local="133233016271190584" remote="133233019060000000" Dst="2" />
<file name="handshake.svg" server="unoriginal.studio//var/www/html/" local="133233016271547590" remote="133233019060000000" Dst="2" />
<file name="hard-drive.svg" server="unoriginal.studio//var/www/html/" local="133233016271906181" remote="133233019070000000" Dst="2" />
<file name="heart.svg" server="unoriginal.studio//var/www/html/" local="133233016272221498" remote="133233019070000000" Dst="2" />
<file name="hospital.svg" server="unoriginal.studio//var/www/html/" local="133233016272454850" remote="133233019070000000" Dst="2" />
<file name="hourglass-half.svg" server="unoriginal.studio//var/www/html/" local="133233016272706121" remote="133233019070000000" Dst="2" />
<file name="hourglass.svg" server="unoriginal.studio//var/www/html/" local="133233016272946367" remote="133233019070000000" Dst="2" />
<file name="id-badge.svg" server="unoriginal.studio//var/www/html/" local="133233016273190025" remote="133233019070000000" Dst="2" />
<file name="id-card.svg" server="unoriginal.studio//var/www/html/" local="133233016273434794" remote="133233019070000000" Dst="2" />
<file name="image.svg" server="unoriginal.studio//var/www/html/" local="133233016273669719" remote="133233019080000000" Dst="2" />
<file name="images.svg" server="unoriginal.studio//var/www/html/" local="133233016273911109" remote="133233019080000000" Dst="2" />
<file name="keyboard.svg" server="unoriginal.studio//var/www/html/" local="133233016274155024" remote="133233019080000000" Dst="2" />
<file name="lemon.svg" server="unoriginal.studio//var/www/html/" local="133233016274424837" remote="133233019080000000" Dst="2" />
<file name="life-ring.svg" server="unoriginal.studio//var/www/html/" local="133233016274698036" remote="133233019080000000" Dst="2" />
<file name="lightbulb.svg" server="unoriginal.studio//var/www/html/" local="133233016274970265" remote="133233019080000000" Dst="2" />
<file name="map.svg" server="unoriginal.studio//var/www/html/" local="133233016275235803" remote="133233019080000000" Dst="2" />
<file name="message.svg" server="unoriginal.studio//var/www/html/" local="133233016275511141" remote="133233019080000000" Dst="2" />
<file name="money-bill-1.svg" server="unoriginal.studio//var/www/html/" local="133233016275751421" remote="133233019090000000" Dst="2" />
<file name="moon.svg" server="unoriginal.studio//var/www/html/" local="133233016276014292" remote="133233019090000000" Dst="2" />
<file name="newspaper.svg" server="unoriginal.studio//var/www/html/" local="133233016276280479" remote="133233019090000000" Dst="2" />
<file name="note-sticky.svg" server="unoriginal.studio//var/www/html/" local="133233016276577860" remote="133233019090000000" Dst="2" />
<file name="object-group.svg" server="unoriginal.studio//var/www/html/" local="133233016276871460" remote="133233019090000000" Dst="2" />
<file name="object-ungroup.svg" server="unoriginal.studio//var/www/html/" local="133233016277124496" remote="133233019090000000" Dst="2" />
<file name="paper-plane.svg" server="unoriginal.studio//var/www/html/" local="133233016277384845" remote="133233019090000000" Dst="2" />
<file name="paste.svg" server="unoriginal.studio//var/www/html/" local="133233016277650695" remote="133233019090000000" Dst="2" />
<file name="pen-to-square.svg" server="unoriginal.studio//var/www/html/" local="133233016277895106" remote="133233019090000000" Dst="2" />
<file name="rectangle-list.svg" server="unoriginal.studio//var/www/html/" local="133233016278119738" remote="133233019100000000" Dst="2" />
<file name="rectangle-xmark.svg" server="unoriginal.studio//var/www/html/" local="133233016278399598" remote="133233019100000000" Dst="2" />
<file name="registered.svg" server="unoriginal.studio//var/www/html/" local="133233016278735604" remote="133233019100000000" Dst="2" />
<file name="share-from-square.svg" server="unoriginal.studio//var/www/html/" local="133233016279106872" remote="133233019100000000" Dst="2" />
<file name="snowflake.svg" server="unoriginal.studio//var/www/html/" local="133233016279385210" remote="133233019100000000" Dst="2" />
<file name="square-caret-down.svg" server="unoriginal.studio//var/www/html/" local="133233016279680443" remote="133233019100000000" Dst="2" />
<file name="square-caret-left.svg" server="unoriginal.studio//var/www/html/" local="133233016280062396" remote="133233019100000000" Dst="2" />
<file name="square-caret-right.svg" server="unoriginal.studio//var/www/html/" local="133233016280368235" remote="133233019100000000" Dst="2" />
<file name="square-caret-up.svg" server="unoriginal.studio//var/www/html/" local="133233016280670569" remote="133233019110000000" Dst="2" />
<file name="square-check.svg" server="unoriginal.studio//var/www/html/" local="133233016280981395" remote="133233019110000000" Dst="2" />
<file name="square-full.svg" server="unoriginal.studio//var/www/html/" local="133233016281336280" remote="133233019110000000" Dst="2" />
<file name="square-minus.svg" server="unoriginal.studio//var/www/html/" local="133233016281667554" remote="133233019110000000" Dst="2" />
<file name="square-plus.svg" server="unoriginal.studio//var/www/html/" local="133233016281943455" remote="133233019110000000" Dst="2" />
<file name="square.svg" server="unoriginal.studio//var/www/html/" local="133233016282235849" remote="133233019110000000" Dst="2" />
<file name="star-half-stroke.svg" server="unoriginal.studio//var/www/html/" local="133233016282501532" remote="133233019110000000" Dst="2" />
<file name="star-half.svg" server="unoriginal.studio//var/www/html/" local="133233016282731075" remote="133233019110000000" Dst="2" />
<file name="star.svg" server="unoriginal.studio//var/www/html/" local="133233016282985328" remote="133233019120000000" Dst="2" />
<file name="sun.svg" server="unoriginal.studio//var/www/html/" local="133233016283230424" remote="133233019120000000" Dst="2" />
<file name="thumbs-down.svg" server="unoriginal.studio//var/www/html/" local="133233016283466136" remote="133233019120000000" Dst="2" />
<file name="thumbs-up.svg" server="unoriginal.studio//var/www/html/" local="133233016283699528" remote="133233019120000000" Dst="2" />
<file name="trash-can.svg" server="unoriginal.studio//var/www/html/" local="133233016283914794" remote="133233019120000000" Dst="2" />
<file name="user.svg" server="unoriginal.studio//var/www/html/" local="133233016284135312" remote="133233019120000000" Dst="2" />
<file name="window-maximize.svg" server="unoriginal.studio//var/www/html/" local="133233016284395735" remote="133233019120000000" Dst="2" />
<file name="window-minimize.svg" server="unoriginal.studio//var/www/html/" local="133233016284661338" remote="133233019120000000" Dst="2" />
<file name="window-restore.svg" server="unoriginal.studio//var/www/html/" local="133233016284909887" remote="133233019120000000" Dst="2" />
</dwsync>